persipy/__init__.py
persipy/entity.py
persipy/repository.py
persipy-0.0.3.dist-info/LICENSE
persipy-0.0.3.dist-info/METADATA
persipy-0.0.3.dist-info/WHEEL
persipy-0.0.3.dist-info/top_level.txt
persipy-0.0.3.dist-info/RECORD
