Metadata-Version: 2.1
Name: persipy
Version: 0.0.3
Summary: Persistence API for Python
Home-page: https://github.com/pristupa/persipy
Author: Pavel V. Pristupa
Author-email: pristupa@gmail.com
License: UNKNOWN
Platform: UNKNOWN
Classifier: Programming Language :: Python :: 3
Classifier: License :: OSI Approved :: GNU General Public License v3 (GPLv3)
Classifier: Operating System :: OS Independent
Requires-Python: >=3.6
